axdocsystem/.vscode/launch.json
axdocsystem/__main__.py
axdocsystem/alembic.ini
axdocsystem/db/__init__.py
axdocsystem/db/alembic_migrations/README
axdocsystem/db/alembic_migrations/env.py
axdocsystem/db/alembic_migrations/script.py.mako
axdocsystem/db/alembic_migrations/versions/766f95525665_first_user.py
axdocsystem/db/alembic_migrations/versions/d14296ae5e11_initialize.py
axdocsystem/db/collection.py
axdocsystem/db/enums.py
axdocsystem/db/models.py
axdocsystem/db/repository/__init__.py
axdocsystem/db/repository/base.py
axdocsystem/db/repository/department.py
axdocsystem/db/repository/document.py
axdocsystem/db/repository/organization.py
axdocsystem/db/repository/users.py
axdocsystem/db/schemas.py
axdocsystem/db/types.py
axdocsystem/src/__init__.py
axdocsystem/src/api/__init__.py
axdocsystem/src/api/auth.py
axdocsystem/src/api/base.py
axdocsystem/src/api/base_crud_api.py
axdocsystem/src/api/base_router.py
axdocsystem/src/api/department.py
axdocsystem/src/api/document.py
axdocsystem/src/api/organization.py
axdocsystem/src/api/registrator.py
axdocsystem/src/api/schemas.py
axdocsystem/src/api/users.py
axdocsystem/src/app.py
axdocsystem/src/db.py
axdocsystem/src/settings.py
axdocsystem/utils/__init__.py
axdocsystem/utils/admin_one_time_token_manager.py
axdocsystem/utils/auth_system.py
axdocsystem/utils/check_content_type_decorator.py
axdocsystem/utils/document_saver.py
axdocsystem/utils/email_system.py
axdocsystem/utils/exceptions.py
axdocsystem/utils/message_system.py
axdocsystem/utils/message_templates/email_verification.html
axdocsystem/utils/message_templates/forgot_passwd.html
axdocsystem/utils/mock_data.py
axdocsystem/utils/notification_system.py
axdocsystem/utils/pass_salt_generator.py
axdocsystem/utils/settings.py
axdocsystem/utils/utils/__init__.py
axdocsystem/utils/utils/auth_system.py
axdocsystem/utils/utils/one_time_token_manager.py
axdocsystem/utils/utils/settings.py
axdocsystem-0.1.52.dist-info/METADATA
axdocsystem-0.1.52.dist-info/WHEEL
axdocsystem-0.1.52.dist-info/RECORD
