Metadata-Version: 2.1
Name: axdocsystem
Version: 0.1.52
Summary: a simple document managment system, was created for the purpose of submitting a work for uni
Author: axdjuraev
Author-email: axdjuraev@gmail.com
Requires-Python: >=3.10,<4.0
Classifier: Programming Language :: Python :: 3
Classifier: Programming Language :: Python :: 3.10
Classifier: Programming Language :: Python :: 3.11
Classifier: Programming Language :: Python :: 3.12
Requires-Dist: aiofiles (>=23.2.1,<24.0.0)
Requires-Dist: aiosmtplib (>=2.0.2,<3.0.0)
Requires-Dist: aiosqlite (>=0.19.0,<0.20.0)
Requires-Dist: alembic (>=1.12.0,<2.0.0)
Requires-Dist: axsqlalchemy (==0.0.54)
Requires-Dist: fastapi (==0.91.0)
Requires-Dist: fastapi-jwt-auth (==0.5.0)
Requires-Dist: fastapi-pagination (==0.11.4)
Requires-Dist: passlib (>=1.7.4,<2.0.0)
Requires-Dist: pydantic (==1.10.4)
Requires-Dist: python-dotenv (==0.21.1)
Requires-Dist: python-jose (==3.3.0)
Requires-Dist: python-multipart (>=0.0.6,<0.0.7)
Requires-Dist: uvicorn[standart] (>=0.23.2,<0.24.0)
